{
  "meta": {
    "title": "马来西亚5天旅行方案",
    "dates": "2026.08.01 - 08.05",
    "people": "4人｜舒适预算｜上海出发",
    "route": "上海 → 吉隆坡 → 亚庇 → 上海",
    "summary": "上海直飞吉隆坡，城市与文化体验2晚；8/3飞亚庇，海岛、日落和轻户外2晚；8/5亚庇返上海。",
    "version": "2026-06-27"
  },
  "stats": [
    {
      "label": "总天数",
      "value": "5天",
      "note": "8/1-8/5"
    },
    {
      "label": "预算",
      "value": "人均 ¥7,650 起",
      "note": "不含购物，以实际下单为准"
    }
  ],
  "baseRoute": [
    ["8/1", "上海 → 吉隆坡", "国际航班 + 入住KLCC/武吉免登"],
    ["8/2", "吉隆坡城市日", "黑风洞 + 独立广场 + 双子塔"],
    ["8/3", "吉隆坡 → 亚庇", "上午飞亚庇，下午市区与丹绒亚路日落"],
    ["8/4", "亚庇海岛日", "东姑阿都拉曼海洋公园跳岛"],
    ["8/5", "亚庇 → 上海", "轻松退房，机场返程"]
  ],
  "days": [
    {
      "id": "day-1",
      "date": "8/1",
      "day": "D1",
      "title": "上海飞吉隆坡",
      "image": "assets/images/malaysia-day1.webp",
      "base": "住KLCC/武吉免登",
      "theme": "抵达 + 城市夜景",
      "tags": ["交通", "入住", "夜景"],
      "morning": "上海浦东机场出发，飞吉隆坡国际机场。",
      "afternoon": "抵达KLIA后办理入境，乘KLIA Ekspres到KL Sentral后打车，或直接Grab前往KLCC/武吉免登酒店入住。",
      "evening": "轻松逛KLCC公园或武吉免登，晚上看双子塔夜景。",
      "time": "上海→吉隆坡直飞约5小时25分-5小时50分；KLIA→KL Sentral快线约28分钟；KLIA→KLCC/武吉免登Grab约55-80分钟，晚高峰可能更久；酒店→KLCC夜景区约10-20分钟。",
      "hotel": "吉隆坡建议住KLCC或武吉免登：KLCC适合看双子塔和城市夜景，武吉免登餐饮和商场更集中。4人优先订两卧公寓式酒店或两间相邻房。",
      "cost": "约 ¥2060-2860/人：上海飞吉隆坡 ¥1200-1800 + 市内交通 ¥80-140 + 餐饮 ¥180 + 住宿分摊 ¥600-740。",
      "costMin": 2060,
      "costMax": 2860
    },
    {
      "id": "day-2",
      "date": "8/2",
      "day": "D2",
      "title": "吉隆坡文化与城市地标",
      "image": "assets/images/malaysia-day2.webp",
      "base": "住KLCC/武吉免登",
      "theme": "黑风洞 + 城市地标",
      "tags": ["城市", "文化", "夜景"],
      "morning": "打车或轨道交通前往黑风洞，参观彩虹阶梯和主洞区域。",
      "afternoon": "回市区游览独立广场、苏丹阿都沙末大厦、茨厂街或中央艺术坊。",
      "evening": "前往双子塔或KLCC公园，想登塔需提前预约Petronas Twin Towers门票。",
      "time": "KLCC/武吉免登→黑风洞约35-60分钟；黑风洞游览约1.5-2小时；黑风洞→独立广场/中央艺术坊约35-55分钟；市区地标步行串联约2-3小时；市区→双子塔约15-25分钟。",
      "hotel": "继续住吉隆坡同一区域，减少搬运行李。",
      "cost": "约 ¥920-1220/人：餐饮 ¥180 + 市内交通 ¥90-150 + 双子塔登塔/景点预留 ¥50-150 + 住宿分摊 ¥600-740。",
      "costMin": 920,
      "costMax": 1220
    },
    {
      "id": "day-3",
      "date": "8/3",
      "day": "D3",
      "title": "吉隆坡飞亚庇",
      "image": "assets/images/malaysia-day3.webp",
      "base": "住亚庇市区/海滨",
      "theme": "转场 + 日落",
      "tags": ["国内航班", "日落", "海滨"],
      "morning": "从吉隆坡酒店前往机场，飞亚庇国际机场。",
      "afternoon": "抵达亚庇后前往市区或海滨酒店入住，轻松逛加雅街、曙光广场或海滨步道。",
      "evening": "前往丹绒亚路海滩看日落，天气不好则改海鲜晚餐和市区散步。",
      "time": "市区→KLIA约55-80分钟；吉隆坡→亚庇飞行约2小时35分-2小时50分；亚庇机场→市区/海滨约15-25分钟；市区→丹绒亚路海滩约15-25分钟。",
      "hotel": "亚庇建议住市区海滨/加雅街附近：吃饭、码头、机场都方便。想更度假可选丹绒亚路度假酒店，但去码头和市区会稍绕。",
      "cost": "约 ¥1280-1770/人：吉隆坡飞亚庇 ¥400-700 + 两地机场交通 ¥120-190 + 餐饮 ¥180 + 住宿分摊 ¥580-700。",
      "costMin": 1280,
      "costMax": 1770
    },
    {
      "id": "day-4",
      "date": "8/4",
      "day": "D4",
      "title": "亚庇海岛跳岛",
      "image": "assets/images/malaysia-day4.webp",
      "base": "住亚庇市区/海滨",
      "theme": "海岛 + 浮潜",
      "tags": ["海岛", "浮潜", "日落"],
      "morning": "从酒店前往Jesselton Point码头，乘船前往东姑阿都拉曼海洋公园，优先选Manukan或Sapi岛。",
      "afternoon": "岛上浮潜、沙滩休息，按天气和体力选择单岛深玩或双岛跳岛。",
      "evening": "返回亚庇市区，晚上海鲜餐或海滨日落补看。",
      "time": "市区酒店→Jesselton Point约5-15分钟；码头→Manukan/Sapi船程约15-25分钟；岛上游玩约4-5小时；返程上岸后回酒店约10-20分钟。若风浪或雷雨明显，改沙巴大学粉红清真寺、水上清真寺和咖啡馆。",
      "hotel": "继续住亚庇市区/海滨，方便码头往返。",
      "cost": "约 ¥1030-1430/人：餐饮 ¥180 + 跳岛船票/码头费/浮潜装备 ¥220-420 + 市内交通 ¥50-130 + 住宿分摊 ¥580-700。",
      "costMin": 1030,
      "costMax": 1430
    },
    {
      "id": "day-5",
      "date": "8/5",
      "day": "D5",
      "title": "亚庇返上海",
      "image": "assets/images/malaysia-day5.webp",
      "base": "返程",
      "theme": "轻松退房 + 回程",
      "tags": ["返程", "机场", "购物"],
      "morning": "根据航班时间退房，早班机直接前往亚庇机场；晚班机可短逛加雅街或买伴手礼。",
      "afternoon": "从亚庇国际机场飞回上海。",
      "evening": "抵达上海，结束行程。",
      "time": "亚庇市区→亚庇机场约15-25分钟；亚庇→上海直飞约4小时25分-4小时55分；若无合适直飞，转吉隆坡/广州/深圳会增加约3-6小时中转时间。",
      "hotel": "不住宿。",
      "cost": "约 ¥2360-3260/人：亚庇飞上海 ¥2100-3000 + 机场交通 ¥40-80 + 餐饮 ¥180 + 行李/杂费预留 ¥40。",
      "costMin": 2360,
      "costMax": 3260
    }
  ],
  "lodging": [
    {
      "city": "吉隆坡",
      "area": "KLCC / 武吉免登",
      "why": "KLCC更适合夜景、双子塔和轻松城市感；武吉免登更适合餐饮、商场和年轻人晚上活动。两地相距不远，4人建议两卧公寓式酒店或两间相邻房。",
      "price": "舒适型约 ¥2400-3000/晚/4人；景观和泳池更好的酒店公寓会更高。"
    },
    {
      "city": "亚庇",
      "area": "市区海滨 / 加雅街 / Jesselton Point附近",
      "why": "离码头、餐厅、商场和机场都近，最适合只有2晚的行程。想纯度假可住丹绒亚路，但跳岛和吃饭会多花路程。",
      "price": "舒适型约 ¥2300-2800/晚/4人；海景度假酒店通常更高。"
    }
  ],
  "reminders": [
    "中国普通护照游客短期赴马来西亚旅游通常免签，但需按官方要求完成Malaysia Digital Arrival Card（MDAC），并以出发前官方页面为准。",
    "8月马来西亚炎热潮湿，吉隆坡和亚庇都可能短时阵雨；海岛日务必看风浪和雷雨，必要时改市区轻松线。",
    "双子塔登塔、热门酒店和亚庇跳岛建议提前预订；海岛当天带防晒、涉水鞋、防水袋和轻薄外套。",
    "跨城航班建议选8/3上午，避免压缩亚庇日落和第二天海岛安排。"
  ],
  "sources": [
    "Malaysia Digital Arrival Card（MDAC）官方说明：https://www.imi.gov.my/",
    "KLIA Ekspres官方信息：KLIA至KL Sentral约28分钟。",
    "Petronas Twin Towers官方访客信息：https://www.petronastwintowers.com.my/",
    "Sabah Tourism官方目的地信息：https://sabahtourism.com/"
  ]
}
